bugzilla2gitlab/__init__.py
bugzilla2gitlab/config.py
bugzilla2gitlab/migrator.py
bugzilla2gitlab/models.py
bugzilla2gitlab/utils.py
bugzilla2gitlab-2.0.1.data/scripts/bugzilla2gitlab
bugzilla2gitlab-2.0.1.data/scripts/clone_users.py
bugzilla2gitlab-2.0.1.dist-info/LICENSE
bugzilla2gitlab-2.0.1.dist-info/METADATA
bugzilla2gitlab-2.0.1.dist-info/WHEEL
bugzilla2gitlab-2.0.1.dist-info/top_level.txt
bugzilla2gitlab-2.0.1.dist-info/RECORD
