Metadata-Version: 2.1
Name: bugzilla2gitlab
Version: 2.0.1
Summary: An opinionated Bugzilla to Gitlab Issues bug migration tool
Home-page: https://github.com/xmunoz/bugzilla2gitlab
Download-URL: https://github.com/xmunoz/bugzilla2gitlab/archive/master.tar.gz
Author: Cristina Muñoz
Author-email: hi@xmunoz.com
Maintainer: Cristina Muñoz
Maintainer-email: hi@xmunoz.com
License: MIT
Keywords: bugzilla,gitlab,bugtracking,workflow
Platform: UNKNOWN
Classifier: Programming Language :: Python
Classifier: Topic :: Software Development
Classifier: Topic :: Software Development :: Libraries
Classifier: Topic :: Software Development :: Libraries :: Python Modules
Classifier: Topic :: Software Development :: Bug Tracking
License-File: LICENSE
